mirror_playlists/__init__.py
mirror_playlists/main.py
mirror_playlists/mirror_playlists_utils.py
mirror_playlists/test_mirror_playlists_utils.py
mirror_playlists-0.0.2.dist-info/LICENSE
mirror_playlists-0.0.2.dist-info/METADATA
mirror_playlists-0.0.2.dist-info/WHEEL
mirror_playlists-0.0.2.dist-info/entry_points.txt
mirror_playlists-0.0.2.dist-info/top_level.txt
mirror_playlists-0.0.2.dist-info/RECORD
